obsidian_kb/__init__.py
obsidian_kb/batch_processor.py
obsidian_kb/cli.py
obsidian_kb/config.py
obsidian_kb/db_connection_manager.py
obsidian_kb/diagnostics.py
obsidian_kb/embedding_cache.py
obsidian_kb/embedding_service.py
obsidian_kb/error_handler.py
obsidian_kb/file_parsers.py
obsidian_kb/filters.py
obsidian_kb/frontmatter_parser.py
obsidian_kb/fuzzy_matching.py
obsidian_kb/ignore_patterns.py
obsidian_kb/indexing_utils.py
obsidian_kb/interfaces.py
obsidian_kb/lance_db.py
obsidian_kb/mcp_server.py
obsidian_kb/metrics.py
obsidian_kb/normalization.py
obsidian_kb/performance_monitor.py
obsidian_kb/query_parser.py
obsidian_kb/rate_limiter.py
obsidian_kb/recovery.py
obsidian_kb/relative_date_parser.py
obsidian_kb/schema_migrations.py
obsidian_kb/search_logger.py
obsidian_kb/search_optimizer.py
obsidian_kb/search_optimizer_integration.py
obsidian_kb/service_container.py
obsidian_kb/structured_logging.py
obsidian_kb/types.py
obsidian_kb/validation.py
obsidian_kb/vault_indexer.py
obsidian_kb/cli/__init__.py
obsidian_kb/cli/utils.py
obsidian_kb/cli/commands/__init__.py
obsidian_kb/cli/commands/config.py
obsidian_kb/cli/commands/diagnostics.py
obsidian_kb/cli/commands/index.py
obsidian_kb/cli/commands/misc.py
obsidian_kb/cli/commands/search.py
obsidian_kb/cli/commands/service.py
obsidian_kb/cli/commands/vault.py
obsidian_kb/cli/commands/watch.py
obsidian_kb/cli/formatters/__init__.py
obsidian_kb/config/__init__.py
obsidian_kb/config/manager.py
obsidian_kb/config/presets.py
obsidian_kb/config/schema.py
obsidian_kb/core/__init__.py
obsidian_kb/core/connection_manager.py
obsidian_kb/core/data_normalizer.py
obsidian_kb/core/ttl_cache.py
obsidian_kb/enrichment/__init__.py
obsidian_kb/enrichment/contextual_retrieval.py
obsidian_kb/enrichment/knowledge_cluster_service.py
obsidian_kb/enrichment/llm_enrichment_service.py
obsidian_kb/enrichment/prompts.py
obsidian_kb/enrichment/summarization.py
obsidian_kb/enrichment/strategies/__init__.py
obsidian_kb-2.0.7.1.dist-info/METADATA
obsidian_kb-2.0.7.1.dist-info/WHEEL
obsidian_kb-2.0.7.1.dist-info/entry_points.txt
obsidian_kb-2.0.7.1.dist-info/licenses/LICENSE
obsidian_kb-2.0.7.1.dist-info/RECORD
