Metadata-Version: 2.4
Name: obsidian-kb
Version: 2.0.7.1
Summary: Local knowledge base for Obsidian vaults with vector search via MCP (Model Context Protocol)
Author: obsidian-kb contributors
License: MIT
License-File: LICENSE
Keywords: claude,embeddings,knowledge-base,lancedb,mcp,obsidian,ollama,semantic-search,vector-search
Classifier: Development Status :: 5 - Production/Stable
Classifier: Intended Audience :: Developers
Classifier: License :: OSI Approved :: MIT License
Classifier: Programming Language :: Python :: 3
Classifier: Programming Language :: Python :: 3.12
Classifier: Topic :: Scientific/Engineering :: Artificial Intelligence
Classifier: Topic :: Software Development :: Libraries :: Python Modules
Classifier: Topic :: Text Processing :: Indexing
Requires-Python: >=3.12
Requires-Dist: aiohttp>=3.11.0
Requires-Dist: aiosqlite>=0.20.0
Requires-Dist: click>=8.1.8
Requires-Dist: fastmcp>=2.0.0
Requires-Dist: lancedb>=0.17.0
Requires-Dist: psutil>=6.0.0
Requires-Dist: pydantic-settings>=2.7.0
Requires-Dist: pydantic>=2.10.0
Requires-Dist: pypdf>=5.1.0
Requires-Dist: python-docx>=1.1.2
Requires-Dist: pyyaml>=6.0.2
Requires-Dist: rich>=13.9.0
Requires-Dist: watchdog>=6.0.0
Requires-Dist: yandex-cloud-ml-sdk>=0.17.0
